skill_issues/__init__.py
skill_issues/init.py
skill_issues/adr/__init__.py
skill_issues/adr/cli.py
skill_issues/issues/__init__.py
skill_issues/issues/cli.py
skill_issues/issues/store.py
skill_issues/issues/tui.py
skill_issues/sessions/__init__.py
skill_issues/sessions/cli.py
skill_issues/sessions/store.py
skill_issues/sessions/tui.py
skill_issues/tui/__init__.py
skill_issues/skills/adr/SKILL.md
skill_issues/skills/issues/SKILL.md
skill_issues/skills/sessions/SKILL.md
skill_issues-0.1.0.dist-info/METADATA
skill_issues-0.1.0.dist-info/WHEEL
skill_issues-0.1.0.dist-info/entry_points.txt
skill_issues-0.1.0.dist-info/licenses/LICENSE
skill_issues-0.1.0.dist-info/RECORD
