Metadata-Version: 2.4
Name: skill-issues
Version: 0.1.0
Summary: Local-first issue tracking and session memory for Claude Code
Project-URL: Homepage, https://github.com/your-username/skill-issues
Project-URL: Repository, https://github.com/your-username/skill-issues
Author: David Page
License-Expression: MIT
License-File: LICENSE
Keywords: claude-code,cli,issues,sessions,tui
Classifier: Development Status :: 3 - Alpha
Classifier: Environment :: Console
Classifier: Intended Audience :: Developers
Classifier: License :: OSI Approved :: MIT License
Classifier: Programming Language :: Python :: 3
Classifier: Programming Language :: Python :: 3.10
Classifier: Programming Language :: Python :: 3.11
Classifier: Programming Language :: Python :: 3.12
Classifier: Topic :: Software Development :: Bug Tracking
Requires-Python: >=3.10
Requires-Dist: textual>=0.89.0
Provides-Extra: dev
Requires-Dist: pytest-asyncio>=0.24; extra == 'dev'
Requires-Dist: pytest>=8.0; extra == 'dev'
